[{"data": {"concepts": [{"name": "man", "value": 0.9926100373268127, "id": "ai_dxSG2s86", "app_id": "main"}, {"name": "one", "value": 0.984843373298645, "id": "ai_SVshtN54", "app_id": "main"}, {"name": "portrait", "value": 0.9767117500305176, "id": "ai_TJ9wFfK5", "app_id": "main"}, {"name": "adult", "value": 0.9753033518791199, "id": "ai_VPmHr5bm", "app_id": "main"}, {"name": "people", "value": 0.9737931489944458, "id": "ai_l8TKp2h5", "app_id": "main"}, {"name": "outdoors", "value": 0.9457754492759705, "id": "ai_Zmhsv0Ch", "app_id": "main"}, {"name": "war", "value": 0.9262377023696899, "id": "ai_Br1sz8D7", "app_id": "main"}, {"name": "battle", "value": 0.9240379333496094, "id": "ai_XPtvvkfn", "app_id": "main"}, {"name": "military", "value": 0.913719117641449, "id": "ai_0SL2mdXt", "app_id": "main"}, {"name": "weapon", "value": 0.903519868850708, "id": "ai_wPx6P0rV", "app_id": "main"}, {"name": "fine-looking", "value": 0.8948194980621338, "id": "ai_fNR8CQHt", "app_id": "main"}, {"name": "danger", "value": 0.8753284215927124, "id": "ai_6pRrC0WT", "app_id": "main"}, {"name": "wear", "value": 0.8749357461929321, "id": "ai_86sS08Pw", "app_id": "main"}, {"name": "soldier", "value": 0.8695306777954102, "id": "ai_tRD53qvV", "app_id": "main"}, {"name": "looking", "value": 0.8621945977210999, "id": "ai_9fQBzNBM", "app_id": "main"}, {"name": "army", "value": 0.8608812093734741, "id": "ai_QdsVHRFl", "app_id": "main"}, {"name": "serious", "value": 0.8428758382797241, "id": "ai_8H8gb4Z2", "app_id": "main"}, {"name": "gun", "value": 0.841262698173523, "id": "ai_mZNdZkpn", "app_id": "main"}, {"name": "uniform", "value": 0.8292112350463867, "id": "ai_prV3z2tW", "app_id": "main"}, {"name": "police", "value": 0.829005241394043, "id": "ai_vxpRR3nL", "app_id": "main"}]}, "frame_info": {"time": 0, "index": 0}}, {"data": {"concepts": [{"name": "people", "value": 0.9737931489944458, "id": "ai_l8TKp2h5", "app_id": "main"}, {"name": "adult", "value": 0.9510440826416016, "id": "ai_VPmHr5bm", "app_id": "main"}, {"name": "one", "value": 0.9316996335983276, "id": "ai_SVshtN54", "app_id": "main"}, {"name": "man", "value": 0.9104284048080444, "id": "ai_dxSG2s86", "app_id": "main"}, {"name": "war", "value": 0.9046111106872559, "id": "ai_Br1sz8D7", "app_id": "main"}, {"name": "battle", "value": 0.8999627828598022, "id": "ai_XPtvvkfn", "app_id": "main"}, {"name": "wear", "value": 0.8749357461929321, "id": "ai_86sS08Pw", "app_id": "main"}, {"name": "outdoors", "value": 0.8615047931671143, "id": "ai_Zmhsv0Ch", "app_id": "main"}, {"name": "military", "value": 0.855188250541687, "id": "ai_0SL2mdXt", "app_id": "main"}, {"name": "police", "value": 0.829005241394043, "id": "ai_vxpRR3nL", "app_id": "main"}, {"name": "offense", "value": 0.8106766939163208, "id": "ai_4dB4Dh6F", "app_id": "main"}, {"name": "portrait", "value": 0.7677571773529053, "id": "ai_TJ9wFfK5", "app_id": "main"}, {"name": "danger", "value": 0.7501330971717834, "id": "ai_6pRrC0WT", "app_id": "main"}, {"name": "weapon", "value": 0.70281982421875, "id": "ai_wPx6P0rV", "app_id": "main"}, {"name": "subway system", "value": 0.6940744519233704, "id": "ai_SHNDcmJ3", "app_id": "main"}, {"name": "outfit", "value": 0.6902961730957031, "id": "ai_ntt6Zlfl", "app_id": "main"}, {"name": "force", "value": 0.6832908391952515, "id": "ai_PMkd2tgg", "app_id": "main"}, {"name": "city", "value": 0.6826071739196777, "id": "ai_WBQfVV0p", "app_id": "main"}, {"name": "soldier", "value": 0.6820486187934875, "id": "ai_tRD53qvV", "app_id": "main"}, {"name": "rain", "value": 0.6810312271118164, "id": "ai_jLK9qsTw", "app_id": "main"}]}, "frame_info": {"time": 1000, "index": 1}}, {"data": {"concepts": [{"name": "people", "value": 0.9884980916976929, "id": "ai_l8TKp2h5", "app_id": "main"}, {"name": "adult", "value": 0.9510440826416016, "id": "ai_VPmHr5bm", "app_id": "main"}, {"name": "no person", "value": 0.9496743679046631, "id": "ai_786Zr311", "app_id": "main"}, {"name": "one", "value": 0.9316996335983276, "id": "ai_SVshtN54", "app_id": "main"}, {"name": "man", "value": 0.9104284048080444, "id": "ai_dxSG2s86", "app_id": "main"}, {"name": "two", "value": 0.9070066213607788, "id": "ai_94cQBGlt", "app_id": "main"}, {"name": "war", "value": 0.9046111106872559, "id": "ai_Br1sz8D7", "app_id": "main"}, {"name": "battle", "value": 0.8948291540145874, "id": "ai_XPtvvkfn", "app_id": "main"}, {"name": "group", "value": 0.8936823606491089, "id": "ai_bmls4LpL", "app_id": "main"}, {"name": "city", "value": 0.8842735290527344, "id": "ai_WBQfVV0p", "app_id": "main"}, {"name": "indoors", "value": 0.8686729669570923, "id": "ai_Pf2b7clG", "app_id": "main"}, {"name": "business", "value": 0.8624268174171448, "id": "ai_6lhccv44", "app_id": "main"}, {"name": "woman", "value": 0.8620139360427856, "id": "ai_RQccV41p", "app_id": "main"}, {"name": "outdoors", "value": 0.8615047931671143, "id": "ai_Zmhsv0Ch", "app_id": "main"}, {"name": "travel", "value": 0.8559339046478271, "id": "ai_VRmbGVWh", "app_id": "main"}, {"name": "military", "value": 0.855188250541687, "id": "ai_0SL2mdXt", "app_id": "main"}, {"name": "vehicle", "value": 0.8539241552352905, "id": "ai_WTrlNkqM", "app_id": "main"}, {"name": "grinder", "value": 0.852545440196991, "id": "ai_QPk3h1Zk", "app_id": "main"}, {"name": "transportation system", "value": 0.8458425402641296, "id": "ai_Xxjc3MhT", "app_id": "main"}, {"name": "building", "value": 0.8400261402130127, "id": "ai_rsX6XWc2", "app_id": "main"}]}, "frame_info": {"time": 2000, "index": 2}}, {"data": {"concepts": [{"name": "eerie", "value": 0.9925079345703125, "id": "ai_kRLbZdnJ", "app_id": "main"}, {"name": "no person", "value": 0.9922462701797485, "id": "ai_786Zr311", "app_id": "main"}, {"name": "abandoned", "value": 0.9849895238876343, "id": "ai_Nvg2cRvB", "app_id": "main"}, {"name": "water", "value": 0.9721115827560425, "id": "ai_BlL0wSQh", "app_id": "main"}, {"name": "light", "value": 0.9719578623771667, "id": "ai_n9vjC1jB", "app_id": "main"}, {"name": "dark", "value": 0.969109058380127, "id": "ai_4sJLn6nX", "app_id": "main"}, {"name": "reflection", "value": 0.9669346213340759, "id": "ai_mlrv94tv", "app_id": "main"}, {"name": "calamity", "value": 0.9658747911453247, "id": "ai_9pWqzvmM", "app_id": "main"}, {"name": "shadow", "value": 0.9471720457077026, "id": "ai_27pZT42H", "app_id": "main"}, {"name": "architecture", "value": 0.9434940814971924, "id": "ai_FWCjC8jZ", "app_id": "main"}, {"name": "skittish", "value": 0.9418772459030151, "id": "ai_C0wkb36z", "app_id": "main"}, {"name": "broken", "value": 0.941570520401001, "id": "ai_XgCGT9vn", "app_id": "main"}, {"name": "building", "value": 0.9409277439117432, "id": "ai_rsX6XWc2", "app_id": "main"}, {"name": "mine", "value": 0.9367100596427917, "id": "ai_rklKFLk8", "app_id": "main"}, {"name": "grinder", "value": 0.9365116357803345, "id": "ai_QPk3h1Zk", "app_id": "main"}, {"name": "travel", "value": 0.9083817005157471, "id": "ai_VRmbGVWh", "app_id": "main"}, {"name": "industry", "value": 0.9078383445739746, "id": "ai_ggQlMG6W", "app_id": "main"}, {"name": "old", "value": 0.9076342582702637, "id": "ai_S0rvLGPz", "app_id": "main"}, {"name": "demolition", "value": 0.8984911441802979, "id": "ai_79kh7zq3", "app_id": "main"}, {"name": "creepy", "value": 0.8979313373565674, "id": "ai_kFVQq5G5", "app_id": "main"}]}, "frame_info": {"time": 3000, "index": 3}}, {"data": {"concepts": [{"name": "people", "value": 0.9781076908111572, "id": "ai_l8TKp2h5", "app_id": "main"}, {"name": "no person", "value": 0.9599108099937439, "id": "ai_786Zr311", "app_id": "main"}, {"name": "adult", "value": 0.9424608945846558, "id": "ai_VPmHr5bm", "app_id": "main"}, {"name": "one", "value": 0.9316996335983276, "id": "ai_SVshtN54", "app_id": "main"}, {"name": "man", "value": 0.9104284048080444, "id": "ai_dxSG2s86", "app_id": "main"}, {"name": "two", "value": 0.8838286399841309, "id": "ai_94cQBGlt", "app_id": "main"}, {"name": "outdoors", "value": 0.8502016067504883, "id": "ai_Zmhsv0Ch", "app_id": "main"}, {"name": "war", "value": 0.8180222511291504, "id": "ai_Br1sz8D7", "app_id": "main"}, {"name": "light", "value": 0.7957288026809692, "id": "ai_n9vjC1jB", "app_id": "main"}, {"name": "woman", "value": 0.7833586931228638, "id": "ai_RQccV41p", "app_id": "main"}, {"name": "indoors", "value": 0.7791651487350464, "id": "ai_Pf2b7clG", "app_id": "main"}, {"name": "portrait", "value": 0.7677571773529053, "id": "ai_TJ9wFfK5", "app_id": "main"}, {"name": "travel", "value": 0.763748049736023, "id": "ai_VRmbGVWh", "app_id": "main"}, {"name": "action", "value": 0.7421581745147705, "id": "ai_lrTHSPdB", "app_id": "main"}, {"name": "motion", "value": 0.7290934920310974, "id": "ai_FwtMR9mk", "app_id": "main"}, {"name": "transportation system", "value": 0.7054873704910278, "id": "ai_Xxjc3MhT", "app_id": "main"}, {"name": "wear", "value": 0.7025749683380127, "id": "ai_86sS08Pw", "app_id": "main"}, {"name": "calamity", "value": 0.6949493288993835, "id": "ai_9pWqzvmM", "app_id": "main"}, {"name": "city", "value": 0.6826071739196777, "id": "ai_WBQfVV0p", "app_id": "main"}, {"name": "architecture", "value": 0.6804132461547852, "id": "ai_FWCjC8jZ", "app_id": "main"}]}, "frame_info": {"time": 4000, "index": 4}}, {"data": {"concepts": [{"name": "no person", "value": 0.990652859210968, "id": "ai_786Zr311", "app_id": "main"}, {"name": "one", "value": 0.9897303581237793, "id": "ai_SVshtN54", "app_id": "main"}, {"name": "people", "value": 0.9781076908111572, "id": "ai_l8TKp2h5", "app_id": "main"}, {"name": "adult", "value": 0.9424608945846558, "id": "ai_VPmHr5bm", "app_id": "main"}, {"name": "man", "value": 0.9372465014457703, "id": "ai_dxSG2s86", "app_id": "main"}, {"name": "museum", "value": 0.9105261564254761, "id": "ai_Tr4QHrc3", "app_id": "main"}, {"name": "light", "value": 0.8998376131057739, "id": "ai_n9vjC1jB", "app_id": "main"}, {"name": "concert", "value": 0.8970701694488525, "id": "ai_sMbNHMwW", "app_id": "main"}, {"name": "musician", "value": 0.8961078524589539, "id": "ai_S81BZrtF", "app_id": "main"}, {"name": "performance", "value": 0.8954408764839172, "id": "ai_325FlCBf", "app_id": "main"}, {"name": "music", "value": 0.8914039134979248, "id": "ai_k76BrtPJ", "app_id": "main"}, {"name": "two", "value": 0.8838286399841309, "id": "ai_94cQBGlt", "app_id": "main"}, {"name": "outdoors", "value": 0.8796025514602661, "id": "ai_Zmhsv0Ch", "app_id": "main"}, {"name": "portrait", "value": 0.8795667886734009, "id": "ai_TJ9wFfK5", "app_id": "main"}, {"name": "danger", "value": 0.8651466369628906, "id": "ai_6pRrC0WT", "app_id": "main"}, {"name": "singer", "value": 0.8624129295349121, "id": "ai_32STZ9b3", "app_id": "main"}, {"name": "horror", "value": 0.8470543622970581, "id": "ai_w8dV3Fm6", "app_id": "main"}, {"name": "metalwork", "value": 0.8360741138458252, "id": "ai_qkcTd6sX", "app_id": "main"}, {"name": "skittish", "value": 0.835466206073761, "id": "ai_C0wkb36z", "app_id": "main"}, {"name": "illustration", "value": 0.8307508230209351, "id": "ai_Dm5GLXnB", "app_id": "main"}]}, "frame_info": {"time": 5000, "index": 5}}, {"data": {"concepts": [{"name": "no person", "value": 0.9599108099937439, "id": "ai_786Zr311", "app_id": "main"}, {"name": "smoke", "value": 0.9040943384170532, "id": "ai_5cvC29fg", "app_id": "main"}, {"name": "dawn", "value": 0.8776995539665222, "id": "ai_lN6KXkcl", "app_id": "main"}, {"name": "coffee", "value": 0.8667869567871094, "id": "ai_BrnHNkt0", "app_id": "main"}, {"name": "drink", "value": 0.8422001004219055, "id": "ai_zJx6RbxW", "app_id": "main"}, {"name": "traditional", "value": 0.8237690329551697, "id": "ai_XclQc6bP", "app_id": "main"}, {"name": "relaxation", "value": 0.7811078429222107, "id": "ai_DqkHZlVW", "app_id": "main"}, {"name": "disjunct", "value": 0.752068281173706, "id": "ai_ZrZ2XRhk", "app_id": "main"}, {"name": "H2O", "value": 0.7414342164993286, "id": "ai_st5grjcT", "app_id": "main"}, {"name": "cup", "value": 0.7394106984138489, "id": "ai_f6ZJXjXq", "app_id": "main"}, {"name": "hot", "value": 0.7336528301239014, "id": "ai_mrWb5vrZ", "app_id": "main"}, {"name": "flame", "value": 0.7207745313644409, "id": "ai_ghzMM5qc", "app_id": "main"}, {"name": "breakfast", "value": 0.702369213104248, "id": "ai_WbwL0pPL", "app_id": "main"}, {"name": "nature", "value": 0.6938861608505249, "id": "ai_tBcWlsCp", "app_id": "main"}, {"name": "heat", "value": 0.6924248933792114, "id": "ai_C3sXn10x", "app_id": "main"}, {"name": "winter", "value": 0.6878436207771301, "id": "ai_2FHPKk9B", "app_id": "main"}, {"name": "celebration", "value": 0.6831696629524231, "id": "ai_wmbvr5TG", "app_id": "main"}, {"name": "splash", "value": 0.6759263277053833, "id": "ai_drjM2Gj8", "app_id": "main"}, {"name": "steam", "value": 0.6743258833885193, "id": "ai_nwjX0LSK", "app_id": "main"}, {"name": "artistic", "value": 0.6709210872650146, "id": "ai_2Bh4VMrb", "app_id": "main"}]}, "frame_info": {"time": 6000, "index": 6}}, {"data": {"concepts": [{"name": "indoors", "value": 0.9902474880218506, "id": "ai_Pf2b7clG", "app_id": "main"}, {"name": "people", "value": 0.9869548678398132, "id": "ai_l8TKp2h5", "app_id": "main"}, {"name": "adult", "value": 0.9780608415603638, "id": "ai_VPmHr5bm", "app_id": "main"}, {"name": "window", "value": 0.9739518165588379, "id": "ai_VTlCx2f2", "app_id": "main"}, {"name": "offense", "value": 0.9628406763076782, "id": "ai_4dB4Dh6F", "app_id": "main"}, {"name": "door", "value": 0.9596943259239197, "id": "ai_HpvT5hjp", "app_id": "main"}, {"name": "shadow", "value": 0.951374888420105, "id": "ai_27pZT42H", "app_id": "main"}, {"name": "man", "value": 0.9457371830940247, "id": "ai_dxSG2s86", "app_id": "main"}, {"name": "doorway", "value": 0.9408836960792542, "id": "ai_KjTgnL8D", "app_id": "main"}, {"name": "one", "value": 0.939857006072998, "id": "ai_SVshtN54", "app_id": "main"}, {"name": "side view", "value": 0.9307621717453003, "id": "ai_XNzGRk0F", "app_id": "main"}, {"name": "portrait", "value": 0.9102941155433655, "id": "ai_TJ9wFfK5", "app_id": "main"}, {"name": "loneliness", "value": 0.9073042869567871, "id": "ai_CX9D4pVM", "app_id": "main"}, {"name": "dark", "value": 0.9058741331100464, "id": "ai_4sJLn6nX", "app_id": "main"}, {"name": "outdoors", "value": 0.896431565284729, "id": "ai_Zmhsv0Ch", "app_id": "main"}, {"name": "wait", "value": 0.8904989957809448, "id": "ai_ccLhwNtM", "app_id": "main"}, {"name": "museum", "value": 0.8870928287506104, "id": "ai_Tr4QHrc3", "app_id": "main"}, {"name": "woman", "value": 0.8790031671524048, "id": "ai_RQccV41p", "app_id": "main"}, {"name": "silhouette", "value": 0.8742154240608215, "id": "ai_fHKHwJ4R", "app_id": "main"}, {"name": "transportation system", "value": 0.8709216117858887, "id": "ai_Xxjc3MhT", "app_id": "main"}]}, "frame_info": {"time": 7000, "index": 7}}, {"data": {"concepts": [{"name": "dark", "value": 0.988703727722168, "id": "ai_4sJLn6nX", "app_id": "main"}, {"name": "no person", "value": 0.9793534278869629, "id": "ai_786Zr311", "app_id": "main"}, {"name": "horizontal", "value": 0.9762692451477051, "id": "ai_vfV1Zf9w", "app_id": "main"}, {"name": "nature", "value": 0.9588167071342468, "id": "ai_tBcWlsCp", "app_id": "main"}, {"name": "illuminated", "value": 0.9550398588180542, "id": "ai_ccZ7tNd3", "app_id": "main"}, {"name": "vertical", "value": 0.9452004432678223, "id": "ai_ZSKpCCHD", "app_id": "main"}, {"name": "bright", "value": 0.918567419052124, "id": "ai_LxrzLJmf", "app_id": "main"}, {"name": "outdoors", "value": 0.8937344551086426, "id": "ai_Zmhsv0Ch", "app_id": "main"}, {"name": "insubstantial", "value": 0.8737317323684692, "id": "ai_rJGvwlP0", "app_id": "main"}, {"name": "moon", "value": 0.863867998123169, "id": "ai_ZWrPWjZr", "app_id": "main"}, {"name": "design", "value": 0.857266902923584, "id": "ai_cMfj16kJ", "app_id": "main"}, {"name": "square", "value": 0.8492568135261536, "id": "ai_h45ZTxZl", "app_id": "main"}, {"name": "creativity", "value": 0.8249549865722656, "id": "ai_HP6qMkcb", "app_id": "main"}, {"name": "shining", "value": 0.7912266254425049, "id": "ai_LM64MDHs", "app_id": "main"}, {"name": "abstract", "value": 0.7766509056091309, "id": "ai_sTjX6dqC", "app_id": "main"}, {"name": "simplicity", "value": 0.7654784917831421, "id": "ai_g6xHN18L", "app_id": "main"}, {"name": "strength", "value": 0.7616114616394043, "id": "ai_g9P4wd2P", "app_id": "main"}, {"name": "space", "value": 0.7429392337799072, "id": "ai_hlbBknxP", "app_id": "main"}, {"name": "illustration", "value": 0.7262099981307983, "id": "ai_Dm5GLXnB", "app_id": "main"}, {"name": "isolated", "value": 0.7202391624450684, "id": "ai_rxcHpHks", "app_id": "main"}]}, "frame_info": {"time": 8000, "index": 8}}, {"data": {"concepts": [{"name": "people", "value": 0.9869548678398132, "id": "ai_l8TKp2h5", "app_id": "main"}, {"name": "adult", "value": 0.9682546854019165, "id": "ai_VPmHr5bm", "app_id": "main"}, {"name": "one", "value": 0.939857006072998, "id": "ai_SVshtN54", "app_id": "main"}, {"name": "portrait", "value": 0.9102941155433655, "id": "ai_TJ9wFfK5", "app_id": "main"}, {"name": "outdoors", "value": 0.8937344551086426, "id": "ai_Zmhsv0Ch", "app_id": "main"}, {"name": "man", "value": 0.8892172574996948, "id": "ai_dxSG2s86", "app_id": "main"}, {"name": "woman", "value": 0.8790031671524048, "id": "ai_RQccV41p", "app_id": "main"}, {"name": "wear", "value": 0.8685792684555054, "id": "ai_86sS08Pw", "app_id": "main"}, {"name": "side view", "value": 0.8268991112709045, "id": "ai_XNzGRk0F", "app_id": "main"}, {"name": "no person", "value": 0.7980502843856812, "id": "ai_786Zr311", "app_id": "main"}, {"name": "horizontal", "value": 0.7714756727218628, "id": "ai_vfV1Zf9w", "app_id": "main"}, {"name": "indoors", "value": 0.747314453125, "id": "ai_Pf2b7clG", "app_id": "main"}, {"name": "city", "value": 0.7273582816123962, "id": "ai_WBQfVV0p", "app_id": "main"}, {"name": "building", "value": 0.7184560894966125, "id": "ai_rsX6XWc2", "app_id": "main"}, {"name": "light", "value": 0.7114185690879822, "id": "ai_n9vjC1jB", "app_id": "main"}, {"name": "street", "value": 0.649960458278656, "id": "ai_GjVpxXrs", "app_id": "main"}, {"name": "vertical", "value": 0.6451438665390015, "id": "ai_ZSKpCCHD", "app_id": "main"}, {"name": "art", "value": 0.6387274265289307, "id": "ai_JBPqff8z", "app_id": "main"}, {"name": "motion", "value": 0.6380516886711121, "id": "ai_FwtMR9mk", "app_id": "main"}, {"name": "two", "value": 0.6341587901115417, "id": "ai_94cQBGlt", "app_id": "main"}]}, "frame_info": {"time": 9000, "index": 9}}, {"data": {"concepts": [{"name": "no person", "value": 0.9945515394210815, "id": "ai_786Zr311", "app_id": "main"}, {"name": "people", "value": 0.9819199442863464, "id": "ai_l8TKp2h5", "app_id": "main"}, {"name": "one", "value": 0.9805262088775635, "id": "ai_SVshtN54", "app_id": "main"}, {"name": "adult", "value": 0.9538539052009583, "id": "ai_VPmHr5bm", "app_id": "main"}, {"name": "art", "value": 0.9354763031005859, "id": "ai_JBPqff8z", "app_id": "main"}, {"name": "side view", "value": 0.9294557571411133, "id": "ai_XNzGRk0F", "app_id": "main"}, {"name": "outdoors", "value": 0.9272454977035522, "id": "ai_Zmhsv0Ch", "app_id": "main"}, {"name": "man", "value": 0.9221203327178955, "id": "ai_dxSG2s86", "app_id": "main"}, {"name": "panoramic", "value": 0.9126245379447937, "id": "ai_xDBZXVs6", "app_id": "main"}, {"name": "illustration", "value": 0.9039880037307739, "id": "ai_Dm5GLXnB", "app_id": "main"}, {"name": "water", "value": 0.9022085666656494, "id": "ai_BlL0wSQh", "app_id": "main"}, {"name": "painting", "value": 0.8983535766601562, "id": "ai_QrcQWGwJ", "app_id": "main"}, {"name": "two", "value": 0.8742048144340515, "id": "ai_94cQBGlt", "app_id": "main"}, {"name": "travel", "value": 0.8588298559188843, "id": "ai_VRmbGVWh", "app_id": "main"}, {"name": "wear", "value": 0.8447736501693726, "id": "ai_86sS08Pw", "app_id": "main"}, {"name": "desktop", "value": 0.8426233530044556, "id": "ai_Lq00FggW", "app_id": "main"}, {"name": "woman", "value": 0.842125415802002, "id": "ai_RQccV41p", "app_id": "main"}, {"name": "nature", "value": 0.8389463424682617, "id": "ai_tBcWlsCp", "app_id": "main"}, {"name": "abstract", "value": 0.8340432643890381, "id": "ai_sTjX6dqC", "app_id": "main"}, {"name": "fog", "value": 0.8318139314651489, "id": "ai_qvzJ1M01", "app_id": "main"}]}, "frame_info": {"time": 10000, "index": 10}}, {"data": {"concepts": [{"name": "people", "value": 0.9898761510848999, "id": "ai_l8TKp2h5", "app_id": "main"}, {"name": "adult", "value": 0.9851399660110474, "id": "ai_VPmHr5bm", "app_id": "main"}, {"name": "one", "value": 0.9788793325424194, "id": "ai_SVshtN54", "app_id": "main"}, {"name": "portrait", "value": 0.9785243272781372, "id": "ai_TJ9wFfK5", "app_id": "main"}, {"name": "woman", "value": 0.9743973612785339, "id": "ai_RQccV41p", "app_id": "main"}, {"name": "music", "value": 0.9714959859848022, "id": "ai_k76BrtPJ", "app_id": "main"}, {"name": "wear", "value": 0.9696068167686462, "id": "ai_86sS08Pw", "app_id": "main"}, {"name": "musician", "value": 0.9545865058898926, "id": "ai_S81BZrtF", "app_id": "main"}, {"name": "light", "value": 0.9537057280540466, "id": "ai_n9vjC1jB", "app_id": "main"}, {"name": "singer", "value": 0.9464659094810486, "id": "ai_32STZ9b3", "app_id": "main"}, {"name": "performance", "value": 0.9441973567008972, "id": "ai_325FlCBf", "app_id": "main"}, {"name": "blur", "value": 0.9388173818588257, "id": "ai_l4WckcJN", "app_id": "main"}, {"name": "festival", "value": 0.9386022090911865, "id": "ai_13NdwKqz", "app_id": "main"}, {"name": "theater", "value": 0.932321310043335, "id": "ai_x1m1q879", "app_id": "main"}, {"name": "actress", "value": 0.924564003944397, "id": "ai_MMxKGmfT", "app_id": "main"}, {"name": "recreation", "value": 0.9168310165405273, "id": "ai_8Qw6PFLZ", "app_id": "main"}, {"name": "stage", "value": 0.9165784120559692, "id": "ai_213hCgg9", "app_id": "main"}, {"name": "outerwear", "value": 0.8910233974456787, "id": "ai_qX2mzVVX", "app_id": "main"}, {"name": "movie", "value": 0.8894240856170654, "id": "ai_4ScHvd0z", "app_id": "main"}, {"name": "fashionable", "value": 0.8880053758621216, "id": "ai_F7mm63J4", "app_id": "main"}]}, "frame_info": {"time": 11000, "index": 11}}, {"data": {"concepts": [{"name": "no person", "value": 0.9882645010948181, "id": "ai_786Zr311", "app_id": "main"}, {"name": "people", "value": 0.9819199442863464, "id": "ai_l8TKp2h5", "app_id": "main"}, {"name": "adult", "value": 0.9538539052009583, "id": "ai_VPmHr5bm", "app_id": "main"}, {"name": "one", "value": 0.9417474269866943, "id": "ai_SVshtN54", "app_id": "main"}, {"name": "outdoors", "value": 0.9272454977035522, "id": "ai_Zmhsv0Ch", "app_id": "main"}, {"name": "light", "value": 0.8614252805709839, "id": "ai_n9vjC1jB", "app_id": "main"}, {"name": "side view", "value": 0.8571363687515259, "id": "ai_XNzGRk0F", "app_id": "main"}, {"name": "man", "value": 0.8530718088150024, "id": "ai_dxSG2s86", "app_id": "main"}, {"name": "wear", "value": 0.8447736501693726, "id": "ai_86sS08Pw", "app_id": "main"}, {"name": "woman", "value": 0.842125415802002, "id": "ai_RQccV41p", "app_id": "main"}, {"name": "travel", "value": 0.8412387371063232, "id": "ai_VRmbGVWh", "app_id": "main"}, {"name": "two", "value": 0.8353064060211182, "id": "ai_94cQBGlt", "app_id": "main"}, {"name": "blur", "value": 0.7933740615844727, "id": "ai_l4WckcJN", "app_id": "main"}, {"name": "landscape", "value": 0.7823294997215271, "id": "ai_MTvKbKJv", "app_id": "main"}, {"name": "nature", "value": 0.7737131118774414, "id": "ai_tBcWlsCp", "app_id": "main"}, {"name": "indoors", "value": 0.747314453125, "id": "ai_Pf2b7clG", "app_id": "main"}, {"name": "portrait", "value": 0.7471570372581482, "id": "ai_TJ9wFfK5", "app_id": "main"}, {"name": "panoramic", "value": 0.7355173826217651, "id": "ai_xDBZXVs6", "app_id": "main"}, {"name": "city", "value": 0.7106183171272278, "id": "ai_WBQfVV0p", "app_id": "main"}, {"name": "sky", "value": 0.682864248752594, "id": "ai_lNsKfmXb", "app_id": "main"}]}, "frame_info": {"time": 12000, "index": 12}}, {"data": {"concepts": [{"name": "no person", "value": 0.9631909132003784, "id": "ai_786Zr311", "app_id": "main"}, {"name": "people", "value": 0.9575132131576538, "id": "ai_l8TKp2h5", "app_id": "main"}, {"name": "outdoors", "value": 0.8915923833847046, "id": "ai_Zmhsv0Ch", "app_id": "main"}, {"name": "one", "value": 0.863705039024353, "id": "ai_SVshtN54", "app_id": "main"}, {"name": "light", "value": 0.8614252805709839, "id": "ai_n9vjC1jB", "app_id": "main"}, {"name": "adult", "value": 0.8602968454360962, "id": "ai_VPmHr5bm", "app_id": "main"}, {"name": "side view", "value": 0.8571363687515259, "id": "ai_XNzGRk0F", "app_id": "main"}, {"name": "horizontal plane", "value": 0.8435527086257935, "id": "ai_8xrjRNnl", "app_id": "main"}, {"name": "landscape", "value": 0.8425018787384033, "id": "ai_MTvKbKJv", "app_id": "main"}, {"name": "travel", "value": 0.8412387371063232, "id": "ai_VRmbGVWh", "app_id": "main"}, {"name": "weather", "value": 0.8392241597175598, "id": "ai_9tsK0tsn", "app_id": "main"}, {"name": "two", "value": 0.8353064060211182, "id": "ai_94cQBGlt", "app_id": "main"}, {"name": "sky", "value": 0.7970882654190063, "id": "ai_lNsKfmXb", "app_id": "main"}, {"name": "blur", "value": 0.7933740615844727, "id": "ai_l4WckcJN", "app_id": "main"}, {"name": "vehicle", "value": 0.7306479215621948, "id": "ai_WTrlNkqM", "app_id": "main"}, {"name": "nature", "value": 0.6689459085464478, "id": "ai_tBcWlsCp", "app_id": "main"}, {"name": "winter", "value": 0.6568899750709534, "id": "ai_2FHPKk9B", "app_id": "main"}, {"name": "daylight", "value": 0.6489730477333069, "id": "ai_ZrPNDjxN", "app_id": "main"}, {"name": "city", "value": 0.6431548595428467, "id": "ai_WBQfVV0p", "app_id": "main"}, {"name": "recreation", "value": 0.6335235834121704, "id": "ai_8Qw6PFLZ", "app_id": "main"}]}, "frame_info": {"time": 13000, "index": 13}}, {"data": {"concepts": [{"name": "no person", "value": 0.9928628206253052, "id": "ai_786Zr311", "app_id": "main"}, {"name": "transportation system", "value": 0.9838072657585144, "id": "ai_Xxjc3MhT", "app_id": "main"}, {"name": "motion", "value": 0.9831231236457825, "id": "ai_FwtMR9mk", "app_id": "main"}, {"name": "outdoors", "value": 0.9808253049850464, "id": "ai_Zmhsv0Ch", "app_id": "main"}, {"name": "travel", "value": 0.9676421284675598, "id": "ai_VRmbGVWh", "app_id": "main"}, {"name": "horizontal plane", "value": 0.9656952619552612, "id": "ai_8xrjRNnl", "app_id": "main"}, {"name": "vehicle", "value": 0.9641043543815613, "id": "ai_WTrlNkqM", "app_id": "main"}, {"name": "water", "value": 0.9581501483917236, "id": "ai_BlL0wSQh", "app_id": "main"}, {"name": "people", "value": 0.9575132131576538, "id": "ai_l8TKp2h5", "app_id": "main"}, {"name": "speed", "value": 0.9513453245162964, "id": "ai_f58d24VF", "app_id": "main"}, {"name": "horizontal", "value": 0.9496802687644958, "id": "ai_vfV1Zf9w", "app_id": "main"}, {"name": "reflection", "value": 0.9454549551010132, "id": "ai_mlrv94tv", "app_id": "main"}, {"name": "sky", "value": 0.9395887851715088, "id": "ai_lNsKfmXb", "app_id": "main"}, {"name": "blur", "value": 0.9296109080314636, "id": "ai_l4WckcJN", "app_id": "main"}, {"name": "daylight", "value": 0.9176899194717407, "id": "ai_ZrPNDjxN", "app_id": "main"}, {"name": "light", "value": 0.9163820743560791, "id": "ai_n9vjC1jB", "app_id": "main"}, {"name": "action", "value": 0.8970444798469543, "id": "ai_lrTHSPdB", "app_id": "main"}, {"name": "panoramic", "value": 0.8956559896469116, "id": "ai_xDBZXVs6", "app_id": "main"}, {"name": "weather", "value": 0.8851470947265625, "id": "ai_9tsK0tsn", "app_id": "main"}, {"name": "landscape", "value": 0.8789743185043335, "id": "ai_MTvKbKJv", "app_id": "main"}]}, "frame_info": {"time": 14000, "index": 14}}, {"data": {"concepts": [{"name": "no person", "value": 0.9849525690078735, "id": "ai_786Zr311", "app_id": "main"}, {"name": "outdoors", "value": 0.9753217697143555, "id": "ai_Zmhsv0Ch", "app_id": "main"}, {"name": "vehicle", "value": 0.9602084755897522, "id": "ai_WTrlNkqM", "app_id": "main"}, {"name": "snow", "value": 0.9562052488327026, "id": "ai_l09WQRHT", "app_id": "main"}, {"name": "winter", "value": 0.9473302364349365, "id": "ai_2FHPKk9B", "app_id": "main"}, {"name": "motion", "value": 0.9304051399230957, "id": "ai_FwtMR9mk", "app_id": "main"}, {"name": "sky", "value": 0.9258185625076294, "id": "ai_lNsKfmXb", "app_id": "main"}, {"name": "transportation system", "value": 0.9207990765571594, "id": "ai_Xxjc3MhT", "app_id": "main"}, {"name": "action", "value": 0.8970444798469543, "id": "ai_lrTHSPdB", "app_id": "main"}, {"name": "weather", "value": 0.8851470947265625, "id": "ai_9tsK0tsn", "app_id": "main"}, {"name": "side view", "value": 0.8764135837554932, "id": "ai_XNzGRk0F", "app_id": "main"}, {"name": "one", "value": 0.863705039024353, "id": "ai_SVshtN54", "app_id": "main"}, {"name": "travel", "value": 0.8572055101394653, "id": "ai_VRmbGVWh", "app_id": "main"}, {"name": "cold", "value": 0.8530919551849365, "id": "ai_2gmKZLxp", "app_id": "main"}, {"name": "horizontal plane", "value": 0.8435527086257935, "id": "ai_8xrjRNnl", "app_id": "main"}, {"name": "landscape", "value": 0.8425018787384033, "id": "ai_MTvKbKJv", "app_id": "main"}, {"name": "aircraft", "value": 0.8316765427589417, "id": "ai_MlJWbCH6", "app_id": "main"}, {"name": "airplane", "value": 0.8228455781936646, "id": "ai_jcThrrq5", "app_id": "main"}, {"name": "people", "value": 0.8214136958122253, "id": "ai_l8TKp2h5", "app_id": "main"}, {"name": "ice", "value": 0.8073437213897705, "id": "ai_jGkHfX9T", "app_id": "main"}]}, "frame_info": {"time": 15000, "index": 15}}, {"data": {"concepts": [{"name": "no person", "value": 0.9847761392593384, "id": "ai_786Zr311", "app_id": "main"}, {"name": "outdoors", "value": 0.9808253049850464, "id": "ai_Zmhsv0Ch", "app_id": "main"}, {"name": "vehicle", "value": 0.9602084755897522, "id": "ai_WTrlNkqM", "app_id": "main"}, {"name": "people", "value": 0.9575132131576538, "id": "ai_l8TKp2h5", "app_id": "main"}, {"name": "snow", "value": 0.9562052488327026, "id": "ai_l09WQRHT", "app_id": "main"}, {"name": "winter", "value": 0.9473302364349365, "id": "ai_2FHPKk9B", "app_id": "main"}, {"name": "motion", "value": 0.9420915842056274, "id": "ai_FwtMR9mk", "app_id": "main"}, {"name": "sky", "value": 0.9258185625076294, "id": "ai_lNsKfmXb", "app_id": "main"}, {"name": "transportation system", "value": 0.9207990765571594, "id": "ai_Xxjc3MhT", "app_id": "main"}, {"name": "action", "value": 0.912034809589386, "id": "ai_lrTHSPdB", "app_id": "main"}, {"name": "one", "value": 0.9037962555885315, "id": "ai_SVshtN54", "app_id": "main"}, {"name": "weather", "value": 0.8851470947265625, "id": "ai_9tsK0tsn", "app_id": "main"}, {"name": "side view", "value": 0.8819100856781006, "id": "ai_XNzGRk0F", "app_id": "main"}, {"name": "adult", "value": 0.8602968454360962, "id": "ai_VPmHr5bm", "app_id": "main"}, {"name": "travel", "value": 0.8572055101394653, "id": "ai_VRmbGVWh", "app_id": "main"}, {"name": "horizontal plane", "value": 0.8435527086257935, "id": "ai_8xrjRNnl", "app_id": "main"}, {"name": "aircraft", "value": 0.8316765427589417, "id": "ai_MlJWbCH6", "app_id": "main"}, {"name": "airplane", "value": 0.8228455781936646, "id": "ai_jcThrrq5", "app_id": "main"}, {"name": "silhouette", "value": 0.8131793141365051, "id": "ai_fHKHwJ4R", "app_id": "main"}, {"name": "landscape", "value": 0.8117882013320923, "id": "ai_MTvKbKJv", "app_id": "main"}]}, "frame_info": {"time": 16000, "index": 16}}, {"data": {"concepts": [{"name": "no person", "value": 0.9631909132003784, "id": "ai_786Zr311", "app_id": "main"}, {"name": "snow", "value": 0.9562052488327026, "id": "ai_l09WQRHT", "app_id": "main"}, {"name": "winter", "value": 0.9473302364349365, "id": "ai_2FHPKk9B", "app_id": "main"}, {"name": "outdoors", "value": 0.9421284198760986, "id": "ai_Zmhsv0Ch", "app_id": "main"}, {"name": "motion", "value": 0.9304051399230957, "id": "ai_FwtMR9mk", "app_id": "main"}, {"name": "action", "value": 0.912034809589386, "id": "ai_lrTHSPdB", "app_id": "main"}, {"name": "one", "value": 0.9037962555885315, "id": "ai_SVshtN54", "app_id": "main"}, {"name": "side view", "value": 0.8819100856781006, "id": "ai_XNzGRk0F", "app_id": "main"}, {"name": "sky", "value": 0.8648934364318848, "id": "ai_lNsKfmXb", "app_id": "main"}, {"name": "people", "value": 0.8412787318229675, "id": "ai_l8TKp2h5", "app_id": "main"}, {"name": "travel", "value": 0.8224685192108154, "id": "ai_VRmbGVWh", "app_id": "main"}, {"name": "weather", "value": 0.82041335105896, "id": "ai_9tsK0tsn", "app_id": "main"}, {"name": "bird", "value": 0.8084694147109985, "id": "ai_G2PvQtHz", "app_id": "main"}, {"name": "adventure", "value": 0.8071584105491638, "id": "ai_nzfkJPGP", "app_id": "main"}, {"name": "ice", "value": 0.8070439100265503, "id": "ai_jGkHfX9T", "app_id": "main"}, {"name": "horizontal plane", "value": 0.7981387376785278, "id": "ai_8xrjRNnl", "app_id": "main"}, {"name": "landscape", "value": 0.7934277057647705, "id": "ai_MTvKbKJv", "app_id": "main"}, {"name": "silhouette", "value": 0.7929188013076782, "id": "ai_fHKHwJ4R", "app_id": "main"}, {"name": "nature", "value": 0.7812097072601318, "id": "ai_tBcWlsCp", "app_id": "main"}, {"name": "adult", "value": 0.7782385349273682, "id": "ai_VPmHr5bm", "app_id": "main"}]}, "frame_info": {"time": 17000, "index": 17}}, {"data": {"concepts": [{"name": "people", "value": 0.9741053581237793, "id": "ai_l8TKp2h5", "app_id": "main"}, {"name": "no person", "value": 0.9464589357376099, "id": "ai_786Zr311", "app_id": "main"}, {"name": "outdoors", "value": 0.9421284198760986, "id": "ai_Zmhsv0Ch", "app_id": "main"}, {"name": "motion", "value": 0.9304051399230957, "id": "ai_FwtMR9mk", "app_id": "main"}, {"name": "one", "value": 0.9037962555885315, "id": "ai_SVshtN54", "app_id": "main"}, {"name": "adult", "value": 0.8944579362869263, "id": "ai_VPmHr5bm", "app_id": "main"}, {"name": "sky", "value": 0.8648934364318848, "id": "ai_lNsKfmXb", "app_id": "main"}, {"name": "winter", "value": 0.81220543384552, "id": "ai_2FHPKk9B", "app_id": "main"}, {"name": "adventure", "value": 0.8071584105491638, "id": "ai_nzfkJPGP", "app_id": "main"}, {"name": "silhouette", "value": 0.7929188013076782, "id": "ai_fHKHwJ4R", "app_id": "main"}, {"name": "action", "value": 0.7868143320083618, "id": "ai_lrTHSPdB", "app_id": "main"}, {"name": "nature", "value": 0.7812097072601318, "id": "ai_tBcWlsCp", "app_id": "main"}, {"name": "danger", "value": 0.7535490989685059, "id": "ai_6pRrC0WT", "app_id": "main"}, {"name": "man", "value": 0.7162342071533203, "id": "ai_dxSG2s86", "app_id": "main"}, {"name": "snow", "value": 0.7093229293823242, "id": "ai_l09WQRHT", "app_id": "main"}, {"name": "side view", "value": 0.6956493854522705, "id": "ai_XNzGRk0F", "app_id": "main"}, {"name": "weather", "value": 0.6853988766670227, "id": "ai_9tsK0tsn", "app_id": "main"}, {"name": "competition", "value": 0.6602033972740173, "id": "ai_7WNVdPhm", "app_id": "main"}, {"name": "travel", "value": 0.6154471039772034, "id": "ai_VRmbGVWh", "app_id": "main"}, {"name": "accident", "value": 0.5959058403968811, "id": "ai_w0Drrqn6", "app_id": "main"}]}, "frame_info": {"time": 18000, "index": 18}}, {"data": {"concepts": [{"name": "people", "value": 0.9741053581237793, "id": "ai_l8TKp2h5", "app_id": "main"}, {"name": "adult", "value": 0.9532802104949951, "id": "ai_VPmHr5bm", "app_id": "main"}, {"name": "outdoors", "value": 0.9246730208396912, "id": "ai_Zmhsv0Ch", "app_id": "main"}, {"name": "one", "value": 0.9090222120285034, "id": "ai_SVshtN54", "app_id": "main"}, {"name": "side view", "value": 0.8819100856781006, "id": "ai_XNzGRk0F", "app_id": "main"}, {"name": "business", "value": 0.8035169839859009, "id": "ai_6lhccv44", "app_id": "main"}, {"name": "nature", "value": 0.7812097072601318, "id": "ai_tBcWlsCp", "app_id": "main"}, {"name": "two", "value": 0.7641739249229431, "id": "ai_94cQBGlt", "app_id": "main"}, {"name": "man", "value": 0.7444406747817993, "id": "ai_dxSG2s86", "app_id": "main"}, {"name": "danger", "value": 0.683182954788208, "id": "ai_6pRrC0WT", "app_id": "main"}, {"name": "sky", "value": 0.6795719265937805, "id": "ai_lNsKfmXb", "app_id": "main"}, {"name": "no person", "value": 0.6769899129867554, "id": "ai_786Zr311", "app_id": "main"}, {"name": "offense", "value": 0.6405545473098755, "id": "ai_4dB4Dh6F", "app_id": "main"}, {"name": "horizontal", "value": 0.5897192358970642, "id": "ai_vfV1Zf9w", "app_id": "main"}, {"name": "action", "value": 0.5655732154846191, "id": "ai_lrTHSPdB", "app_id": "main"}, {"name": "daylight", "value": 0.5653076767921448, "id": "ai_ZrPNDjxN", "app_id": "main"}, {"name": "motion", "value": 0.5638523697853088, "id": "ai_FwtMR9mk", "app_id": "main"}, {"name": "travel", "value": 0.5472338199615479, "id": "ai_VRmbGVWh", "app_id": "main"}, {"name": "vertical", "value": 0.5420161485671997, "id": "ai_ZSKpCCHD", "app_id": "main"}, {"name": "portrait", "value": 0.5284847021102905, "id": "ai_TJ9wFfK5", "app_id": "main"}]}, "frame_info": {"time": 19000, "index": 19}}, {"data": {"concepts": [{"name": "people", "value": 0.9741053581237793, "id": "ai_l8TKp2h5", "app_id": "main"}, {"name": "adult", "value": 0.9532802104949951, "id": "ai_VPmHr5bm", "app_id": "main"}, {"name": "outdoors", "value": 0.9246730208396912, "id": "ai_Zmhsv0Ch", "app_id": "main"}, {"name": "one", "value": 0.9231997728347778, "id": "ai_SVshtN54", "app_id": "main"}, {"name": "business", "value": 0.8035169839859009, "id": "ai_6lhccv44", "app_id": "main"}, {"name": "nature", "value": 0.7812097072601318, "id": "ai_tBcWlsCp", "app_id": "main"}, {"name": "man", "value": 0.7444406747817993, "id": "ai_dxSG2s86", "app_id": "main"}, {"name": "recreation", "value": 0.6960418224334717, "id": "ai_8Qw6PFLZ", "app_id": "main"}, {"name": "side view", "value": 0.6956493854522705, "id": "ai_XNzGRk0F", "app_id": "main"}, {"name": "two", "value": 0.6817122101783752, "id": "ai_94cQBGlt", "app_id": "main"}, {"name": "sky", "value": 0.6795719265937805, "id": "ai_lNsKfmXb", "app_id": "main"}, {"name": "no person", "value": 0.6769899129867554, "id": "ai_786Zr311", "app_id": "main"}, {"name": "offense", "value": 0.6405545473098755, "id": "ai_4dB4Dh6F", "app_id": "main"}, {"name": "horizontal", "value": 0.5897192358970642, "id": "ai_vfV1Zf9w", "app_id": "main"}, {"name": "portrait", "value": 0.581944465637207, "id": "ai_TJ9wFfK5", "app_id": "main"}, {"name": "action", "value": 0.5655732154846191, "id": "ai_lrTHSPdB", "app_id": "main"}, {"name": "daylight", "value": 0.5653076767921448, "id": "ai_ZrPNDjxN", "app_id": "main"}, {"name": "motion", "value": 0.5638523697853088, "id": "ai_FwtMR9mk", "app_id": "main"}, {"name": "travel", "value": 0.5472338199615479, "id": "ai_VRmbGVWh", "app_id": "main"}, {"name": "danger", "value": 0.5445471405982971, "id": "ai_6pRrC0WT", "app_id": "main"}]}, "frame_info": {"time": 20000, "index": 20}}, {"data": {"concepts": [{"name": "people", "value": 0.9741053581237793, "id": "ai_l8TKp2h5", "app_id": "main"}, {"name": "adult", "value": 0.9536741971969604, "id": "ai_VPmHr5bm", "app_id": "main"}, {"name": "one", "value": 0.9314056634902954, "id": "ai_SVshtN54", "app_id": "main"}, {"name": "portrait", "value": 0.9284521341323853, "id": "ai_TJ9wFfK5", "app_id": "main"}, {"name": "man", "value": 0.891843318939209, "id": "ai_dxSG2s86", "app_id": "main"}, {"name": "wear", "value": 0.8513833284378052, "id": "ai_86sS08Pw", "app_id": "main"}, {"name": "outdoors", "value": 0.8400684595108032, "id": "ai_Zmhsv0Ch", "app_id": "main"}, {"name": "business", "value": 0.8035169839859009, "id": "ai_6lhccv44", "app_id": "main"}, {"name": "offense", "value": 0.7677826881408691, "id": "ai_4dB4Dh6F", "app_id": "main"}, {"name": "woman", "value": 0.7499154210090637, "id": "ai_RQccV41p", "app_id": "main"}, {"name": "music", "value": 0.717271089553833, "id": "ai_k76BrtPJ", "app_id": "main"}, {"name": "two", "value": 0.7078601717948914, "id": "ai_94cQBGlt", "app_id": "main"}, {"name": "side view", "value": 0.6956493854522705, "id": "ai_XNzGRk0F", "app_id": "main"}, {"name": "indoors", "value": 0.6851530075073242, "id": "ai_Pf2b7clG", "app_id": "main"}, {"name": "recreation", "value": 0.6208404898643494, "id": "ai_8Qw6PFLZ", "app_id": "main"}, {"name": "musician", "value": 0.6173644065856934, "id": "ai_S81BZrtF", "app_id": "main"}, {"name": "light", "value": 0.5373967885971069, "id": "ai_n9vjC1jB", "app_id": "main"}, {"name": "vehicle", "value": 0.535727858543396, "id": "ai_WTrlNkqM", "app_id": "main"}, {"name": "smoke", "value": 0.5324262380599976, "id": "ai_5cvC29fg", "app_id": "main"}, {"name": "travel", "value": 0.5285994410514832, "id": "ai_VRmbGVWh", "app_id": "main"}]}, "frame_info": {"time": 21000, "index": 21}}, {"data": {"concepts": [{"name": "people", "value": 0.9741053581237793, "id": "ai_l8TKp2h5", "app_id": "main"}, {"name": "adult", "value": 0.9536741971969604, "id": "ai_VPmHr5bm", "app_id": "main"}, {"name": "one", "value": 0.9314056634902954, "id": "ai_SVshtN54", "app_id": "main"}, {"name": "portrait", "value": 0.9284521341323853, "id": "ai_TJ9wFfK5", "app_id": "main"}, {"name": "man", "value": 0.891843318939209, "id": "ai_dxSG2s86", "app_id": "main"}, {"name": "wear", "value": 0.8513833284378052, "id": "ai_86sS08Pw", "app_id": "main"}, {"name": "outdoors", "value": 0.7938246726989746, "id": "ai_Zmhsv0Ch", "app_id": "main"}, {"name": "offense", "value": 0.7677826881408691, "id": "ai_4dB4Dh6F", "app_id": "main"}, {"name": "woman", "value": 0.7499154210090637, "id": "ai_RQccV41p", "app_id": "main"}, {"name": "music", "value": 0.717271089553833, "id": "ai_k76BrtPJ", "app_id": "main"}, {"name": "two", "value": 0.7078601717948914, "id": "ai_94cQBGlt", "app_id": "main"}, {"name": "side view", "value": 0.6974284648895264, "id": "ai_XNzGRk0F", "app_id": "main"}, {"name": "light", "value": 0.6547121405601501, "id": "ai_n9vjC1jB", "app_id": "main"}, {"name": "recreation", "value": 0.6208404898643494, "id": "ai_8Qw6PFLZ", "app_id": "main"}, {"name": "musician", "value": 0.6173644065856934, "id": "ai_S81BZrtF", "app_id": "main"}, {"name": "festival", "value": 0.5697590708732605, "id": "ai_13NdwKqz", "app_id": "main"}, {"name": "vehicle", "value": 0.535727858543396, "id": "ai_WTrlNkqM", "app_id": "main"}, {"name": "smoke", "value": 0.5324262380599976, "id": "ai_5cvC29fg", "app_id": "main"}, {"name": "singer", "value": 0.52194744348526, "id": "ai_32STZ9b3", "app_id": "main"}, {"name": "motion", "value": 0.49406683444976807, "id": "ai_FwtMR9mk", "app_id": "main"}]}, "frame_info": {"time": 22000, "index": 22}}, {"data": {"concepts": [{"name": "people", "value": 0.990052342414856, "id": "ai_l8TKp2h5", "app_id": "main"}, {"name": "no person", "value": 0.9832528829574585, "id": "ai_786Zr311", "app_id": "main"}, {"name": "adult", "value": 0.9498438835144043, "id": "ai_VPmHr5bm", "app_id": "main"}, {"name": "one", "value": 0.9486336708068848, "id": "ai_SVshtN54", "app_id": "main"}, {"name": "man", "value": 0.8843976259231567, "id": "ai_dxSG2s86", "app_id": "main"}, {"name": "offense", "value": 0.8647620677947998, "id": "ai_4dB4Dh6F", "app_id": "main"}, {"name": "outdoors", "value": 0.8400684595108032, "id": "ai_Zmhsv0Ch", "app_id": "main"}, {"name": "wear", "value": 0.8185752630233765, "id": "ai_86sS08Pw", "app_id": "main"}, {"name": "indoors", "value": 0.7754196524620056, "id": "ai_Pf2b7clG", "app_id": "main"}, {"name": "portrait", "value": 0.7748387455940247, "id": "ai_TJ9wFfK5", "app_id": "main"}, {"name": "light", "value": 0.7627450227737427, "id": "ai_n9vjC1jB", "app_id": "main"}, {"name": "music", "value": 0.7593104839324951, "id": "ai_k76BrtPJ", "app_id": "main"}, {"name": "woman", "value": 0.7499154210090637, "id": "ai_RQccV41p", "app_id": "main"}, {"name": "shadow", "value": 0.720517098903656, "id": "ai_27pZT42H", "app_id": "main"}, {"name": "daylight", "value": 0.7048516273498535, "id": "ai_ZrPNDjxN", "app_id": "main"}, {"name": "side view", "value": 0.6974284648895264, "id": "ai_XNzGRk0F", "app_id": "main"}, {"name": "recreation", "value": 0.6960418224334717, "id": "ai_8Qw6PFLZ", "app_id": "main"}, {"name": "two", "value": 0.6817122101783752, "id": "ai_94cQBGlt", "app_id": "main"}, {"name": "blur", "value": 0.6728688478469849, "id": "ai_l4WckcJN", "app_id": "main"}, {"name": "child", "value": 0.6529631614685059, "id": "ai_qcLd7fgc", "app_id": "main"}]}, "frame_info": {"time": 23000, "index": 23}}, {"data": {"concepts": [{"name": "no person", "value": 0.9851897358894348, "id": "ai_786Zr311", "app_id": "main"}, {"name": "one", "value": 0.9486336708068848, "id": "ai_SVshtN54", "app_id": "main"}, {"name": "people", "value": 0.9115327596664429, "id": "ai_l8TKp2h5", "app_id": "main"}, {"name": "outdoors", "value": 0.895033597946167, "id": "ai_Zmhsv0Ch", "app_id": "main"}, {"name": "dark", "value": 0.8927311301231384, "id": "ai_4sJLn6nX", "app_id": "main"}, {"name": "nature", "value": 0.8854798078536987, "id": "ai_tBcWlsCp", "app_id": "main"}, {"name": "adult", "value": 0.8486104011535645, "id": "ai_VPmHr5bm", "app_id": "main"}, {"name": "indoors", "value": 0.7865377068519592, "id": "ai_Pf2b7clG", "app_id": "main"}, {"name": "shadow", "value": 0.7470851540565491, "id": "ai_27pZT42H", "app_id": "main"}, {"name": "illuminated", "value": 0.7307777404785156, "id": "ai_ccZ7tNd3", "app_id": "main"}, {"name": "sky", "value": 0.7043055295944214, "id": "ai_lNsKfmXb", "app_id": "main"}, {"name": "art", "value": 0.6892493367195129, "id": "ai_JBPqff8z", "app_id": "main"}, {"name": "recreation", "value": 0.6208404898643494, "id": "ai_8Qw6PFLZ", "app_id": "main"}, {"name": "silhouette", "value": 0.6170898079872131, "id": "ai_fHKHwJ4R", "app_id": "main"}, {"name": "old", "value": 0.5998398065567017, "id": "ai_S0rvLGPz", "app_id": "main"}, {"name": "portrait", "value": 0.581944465637207, "id": "ai_TJ9wFfK5", "app_id": "main"}, {"name": "eerie", "value": 0.5764948129653931, "id": "ai_kRLbZdnJ", "app_id": "main"}, {"name": "side view", "value": 0.573093831539154, "id": "ai_XNzGRk0F", "app_id": "main"}, {"name": "smoke", "value": 0.5566866397857666, "id": "ai_5cvC29fg", "app_id": "main"}, {"name": "two", "value": 0.5517978668212891, "id": "ai_94cQBGlt", "app_id": "main"}]}, "frame_info": {"time": 24000, "index": 24}}, {"data": {"concepts": [{"name": "people", "value": 0.990052342414856, "id": "ai_l8TKp2h5", "app_id": "main"}, {"name": "light", "value": 0.987306535243988, "id": "ai_n9vjC1jB", "app_id": "main"}, {"name": "no person", "value": 0.9832528829574585, "id": "ai_786Zr311", "app_id": "main"}, {"name": "one", "value": 0.9782500267028809, "id": "ai_SVshtN54", "app_id": "main"}, {"name": "shadow", "value": 0.9765211343765259, "id": "ai_27pZT42H", "app_id": "main"}, {"name": "adult", "value": 0.9498438835144043, "id": "ai_VPmHr5bm", "app_id": "main"}, {"name": "religion", "value": 0.9408302307128906, "id": "ai_358VqvJT", "app_id": "main"}, {"name": "indoors", "value": 0.9355382919311523, "id": "ai_Pf2b7clG", "app_id": "main"}, {"name": "eerie", "value": 0.9167850017547607, "id": "ai_kRLbZdnJ", "app_id": "main"}, {"name": "music", "value": 0.9065719842910767, "id": "ai_k76BrtPJ", "app_id": "main"}, {"name": "musician", "value": 0.9008216261863708, "id": "ai_S81BZrtF", "app_id": "main"}, {"name": "outdoors", "value": 0.895033597946167, "id": "ai_Zmhsv0Ch", "app_id": "main"}, {"name": "window", "value": 0.894922137260437, "id": "ai_VTlCx2f2", "app_id": "main"}, {"name": "dark", "value": 0.8927311301231384, "id": "ai_4sJLn6nX", "app_id": "main"}, {"name": "mystery", "value": 0.8919732570648193, "id": "ai_BbM8D022", "app_id": "main"}, {"name": "offense", "value": 0.8898794651031494, "id": "ai_4dB4Dh6F", "app_id": "main"}, {"name": "man", "value": 0.8843976259231567, "id": "ai_dxSG2s86", "app_id": "main"}, {"name": "festival", "value": 0.8777555227279663, "id": "ai_13NdwKqz", "app_id": "main"}, {"name": "performance", "value": 0.8746945858001709, "id": "ai_325FlCBf", "app_id": "main"}, {"name": "daylight", "value": 0.8742191791534424, "id": "ai_ZrPNDjxN", "app_id": "main"}]}, "frame_info": {"time": 25000, "index": 25}}, {"data": {"concepts": [{"name": "no person", "value": 0.9832528829574585, "id": "ai_786Zr311", "app_id": "main"}, {"name": "people", "value": 0.975412130355835, "id": "ai_l8TKp2h5", "app_id": "main"}, {"name": "light", "value": 0.9665477275848389, "id": "ai_n9vjC1jB", "app_id": "main"}, {"name": "outdoors", "value": 0.9306026697158813, "id": "ai_Zmhsv0Ch", "app_id": "main"}, {"name": "adult", "value": 0.8963002562522888, "id": "ai_VPmHr5bm", "app_id": "main"}, {"name": "dark", "value": 0.8927311301231384, "id": "ai_4sJLn6nX", "app_id": "main"}, {"name": "man", "value": 0.8843976259231567, "id": "ai_dxSG2s86", "app_id": "main"}, {"name": "one", "value": 0.8800212144851685, "id": "ai_SVshtN54", "app_id": "main"}, {"name": "festival", "value": 0.8777555227279663, "id": "ai_13NdwKqz", "app_id": "main"}, {"name": "city", "value": 0.8214844465255737, "id": "ai_WBQfVV0p", "app_id": "main"}, {"name": "blur", "value": 0.8121606111526489, "id": "ai_l4WckcJN", "app_id": "main"}, {"name": "shadow", "value": 0.8070139288902283, "id": "ai_27pZT42H", "app_id": "main"}, {"name": "performance", "value": 0.8009389638900757, "id": "ai_325FlCBf", "app_id": "main"}, {"name": "indoors", "value": 0.7685245871543884, "id": "ai_Pf2b7clG", "app_id": "main"}, {"name": "eerie", "value": 0.7624317407608032, "id": "ai_kRLbZdnJ", "app_id": "main"}, {"name": "portrait", "value": 0.7458047866821289, "id": "ai_TJ9wFfK5", "app_id": "main"}, {"name": "illuminated", "value": 0.7307777404785156, "id": "ai_ccZ7tNd3", "app_id": "main"}, {"name": "offense", "value": 0.7303059101104736, "id": "ai_4dB4Dh6F", "app_id": "main"}, {"name": "backlit", "value": 0.709583580493927, "id": "ai_WcnFrjw1", "app_id": "main"}, {"name": "woman", "value": 0.7067157030105591, "id": "ai_RQccV41p", "app_id": "main"}]}, "frame_info": {"time": 26000, "index": 26}}, {"data": {"concepts": [{"name": "no person", "value": 0.9832528829574585, "id": "ai_786Zr311", "app_id": "main"}, {"name": "people", "value": 0.975412130355835, "id": "ai_l8TKp2h5", "app_id": "main"}, {"name": "light", "value": 0.9665477275848389, "id": "ai_n9vjC1jB", "app_id": "main"}, {"name": "outdoors", "value": 0.9306026697158813, "id": "ai_Zmhsv0Ch", "app_id": "main"}, {"name": "one", "value": 0.9131919741630554, "id": "ai_SVshtN54", "app_id": "main"}, {"name": "adult", "value": 0.8963002562522888, "id": "ai_VPmHr5bm", "app_id": "main"}, {"name": "dark", "value": 0.8927311301231384, "id": "ai_4sJLn6nX", "app_id": "main"}, {"name": "religion", "value": 0.8925607800483704, "id": "ai_358VqvJT", "app_id": "main"}, {"name": "man", "value": 0.8843976259231567, "id": "ai_dxSG2s86", "app_id": "main"}, {"name": "festival", "value": 0.8777555227279663, "id": "ai_13NdwKqz", "app_id": "main"}, {"name": "city", "value": 0.8214844465255737, "id": "ai_WBQfVV0p", "app_id": "main"}, {"name": "blur", "value": 0.8121606111526489, "id": "ai_l4WckcJN", "app_id": "main"}, {"name": "performance", "value": 0.8009389638900757, "id": "ai_325FlCBf", "app_id": "main"}, {"name": "travel", "value": 0.7874934077262878, "id": "ai_VRmbGVWh", "app_id": "main"}, {"name": "indoors", "value": 0.7685245871543884, "id": "ai_Pf2b7clG", "app_id": "main"}, {"name": "daylight", "value": 0.7632054686546326, "id": "ai_ZrPNDjxN", "app_id": "main"}, {"name": "portrait", "value": 0.7612205743789673, "id": "ai_TJ9wFfK5", "app_id": "main"}, {"name": "shadow", "value": 0.7470851540565491, "id": "ai_27pZT42H", "app_id": "main"}, {"name": "illuminated", "value": 0.7438362836837769, "id": "ai_ccZ7tNd3", "app_id": "main"}, {"name": "offense", "value": 0.7303059101104736, "id": "ai_4dB4Dh6F", "app_id": "main"}]}, "frame_info": {"time": 27000, "index": 27}}, {"data": {"concepts": [{"name": "people", "value": 0.975412130355835, "id": "ai_l8TKp2h5", "app_id": "main"}, {"name": "light", "value": 0.9557352066040039, "id": "ai_n9vjC1jB", "app_id": "main"}, {"name": "outdoors", "value": 0.9306026697158813, "id": "ai_Zmhsv0Ch", "app_id": "main"}, {"name": "one", "value": 0.9131919741630554, "id": "ai_SVshtN54", "app_id": "main"}, {"name": "man", "value": 0.8972581624984741, "id": "ai_dxSG2s86", "app_id": "main"}, {"name": "adult", "value": 0.8963002562522888, "id": "ai_VPmHr5bm", "app_id": "main"}, {"name": "dark", "value": 0.8388996124267578, "id": "ai_4sJLn6nX", "app_id": "main"}, {"name": "no person", "value": 0.8271093368530273, "id": "ai_786Zr311", "app_id": "main"}, {"name": "blur", "value": 0.8121606111526489, "id": "ai_l4WckcJN", "app_id": "main"}, {"name": "festival", "value": 0.8032644987106323, "id": "ai_13NdwKqz", "app_id": "main"}, {"name": "performance", "value": 0.8009389638900757, "id": "ai_325FlCBf", "app_id": "main"}, {"name": "portrait", "value": 0.7612205743789673, "id": "ai_TJ9wFfK5", "app_id": "main"}, {"name": "city", "value": 0.7535704374313354, "id": "ai_WBQfVV0p", "app_id": "main"}, {"name": "offense", "value": 0.7303059101104736, "id": "ai_4dB4Dh6F", "app_id": "main"}, {"name": "recreation", "value": 0.7277866005897522, "id": "ai_8Qw6PFLZ", "app_id": "main"}, {"name": "shadow", "value": 0.7226473689079285, "id": "ai_27pZT42H", "app_id": "main"}, {"name": "danger", "value": 0.7090088725090027, "id": "ai_6pRrC0WT", "app_id": "main"}, {"name": "action", "value": 0.7071573138237, "id": "ai_lrTHSPdB", "app_id": "main"}, {"name": "woman", "value": 0.7067157030105591, "id": "ai_RQccV41p", "app_id": "main"}, {"name": "competition", "value": 0.6962026357650757, "id": "ai_7WNVdPhm", "app_id": "main"}]}, "frame_info": {"time": 28000, "index": 28}}, {"data": {"concepts": [{"name": "no person", "value": 0.992031455039978, "id": "ai_786Zr311", "app_id": "main"}, {"name": "dark", "value": 0.9621055126190186, "id": "ai_4sJLn6nX", "app_id": "main"}, {"name": "people", "value": 0.9609864950180054, "id": "ai_l8TKp2h5", "app_id": "main"}, {"name": "light", "value": 0.9557352066040039, "id": "ai_n9vjC1jB", "app_id": "main"}, {"name": "blur", "value": 0.9463926553726196, "id": "ai_l4WckcJN", "app_id": "main"}, {"name": "illuminated", "value": 0.9289178848266602, "id": "ai_ccZ7tNd3", "app_id": "main"}, {"name": "desktop", "value": 0.916324257850647, "id": "ai_Lq00FggW", "app_id": "main"}, {"name": "mystery", "value": 0.9149326086044312, "id": "ai_BbM8D022", "app_id": "main"}, {"name": "one", "value": 0.9131919741630554, "id": "ai_SVshtN54", "app_id": "main"}, {"name": "outdoors", "value": 0.9082959890365601, "id": "ai_Zmhsv0Ch", "app_id": "main"}, {"name": "insubstantial", "value": 0.900371789932251, "id": "ai_rJGvwlP0", "app_id": "main"}, {"name": "religion", "value": 0.8925607800483704, "id": "ai_358VqvJT", "app_id": "main"}, {"name": "art", "value": 0.8777773380279541, "id": "ai_JBPqff8z", "app_id": "main"}, {"name": "travel", "value": 0.8773625493049622, "id": "ai_VRmbGVWh", "app_id": "main"}, {"name": "abstract", "value": 0.8762675523757935, "id": "ai_sTjX6dqC", "app_id": "main"}, {"name": "adult", "value": 0.8711735010147095, "id": "ai_VPmHr5bm", "app_id": "main"}, {"name": "lamp", "value": 0.8498399257659912, "id": "ai_TXJ61ckM", "app_id": "main"}, {"name": "color", "value": 0.8404584527015686, "id": "ai_0JbWBDPd", "app_id": "main"}, {"name": "nature", "value": 0.8402020931243896, "id": "ai_tBcWlsCp", "app_id": "main"}, {"name": "silhouette", "value": 0.839192271232605, "id": "ai_fHKHwJ4R", "app_id": "main"}]}, "frame_info": {"time": 29000, "index": 29}}, {"data": {"concepts": [{"name": "one", "value": 0.9961980581283569, "id": "ai_SVshtN54", "app_id": "main"}, {"name": "people", "value": 0.9957295656204224, "id": "ai_l8TKp2h5", "app_id": "main"}, {"name": "adult", "value": 0.9891029000282288, "id": "ai_VPmHr5bm", "app_id": "main"}, {"name": "portrait", "value": 0.9701676368713379, "id": "ai_TJ9wFfK5", "app_id": "main"}, {"name": "man", "value": 0.9572210311889648, "id": "ai_dxSG2s86", "app_id": "main"}, {"name": "weapon", "value": 0.9405511617660522, "id": "ai_wPx6P0rV", "app_id": "main"}, {"name": "wear", "value": 0.9338983297348022, "id": "ai_86sS08Pw", "app_id": "main"}, {"name": "recreation", "value": 0.9303684234619141, "id": "ai_8Qw6PFLZ", "app_id": "main"}, {"name": "competition", "value": 0.9209840297698975, "id": "ai_7WNVdPhm", "app_id": "main"}, {"name": "musician", "value": 0.889694094657898, "id": "ai_S81BZrtF", "app_id": "main"}, {"name": "gun", "value": 0.886186957359314, "id": "ai_mZNdZkpn", "app_id": "main"}, {"name": "athlete", "value": 0.885980486869812, "id": "ai_fhqpCCSD", "app_id": "main"}, {"name": "woman", "value": 0.881907045841217, "id": "ai_RQccV41p", "app_id": "main"}, {"name": "music", "value": 0.8765361309051514, "id": "ai_k76BrtPJ", "app_id": "main"}, {"name": "outfit", "value": 0.868132472038269, "id": "ai_ntt6Zlfl", "app_id": "main"}, {"name": "danger", "value": 0.8608119487762451, "id": "ai_6pRrC0WT", "app_id": "main"}, {"name": "two", "value": 0.8541242480278015, "id": "ai_94cQBGlt", "app_id": "main"}, {"name": "offense", "value": 0.8534195423126221, "id": "ai_4dB4Dh6F", "app_id": "main"}, {"name": "singer", "value": 0.8374884128570557, "id": "ai_32STZ9b3", "app_id": "main"}, {"name": "action", "value": 0.8346319198608398, "id": "ai_lrTHSPdB", "app_id": "main"}]}, "frame_info": {"time": 30000, "index": 30}}, {"data": {"concepts": [{"name": "people", "value": 0.9946573376655579, "id": "ai_l8TKp2h5", "app_id": "main"}, {"name": "adult", "value": 0.9891029000282288, "id": "ai_VPmHr5bm", "app_id": "main"}, {"name": "man", "value": 0.9572210311889648, "id": "ai_dxSG2s86", "app_id": "main"}, {"name": "portrait", "value": 0.9567321538925171, "id": "ai_TJ9wFfK5", "app_id": "main"}, {"name": "one", "value": 0.9426029920578003, "id": "ai_SVshtN54", "app_id": "main"}, {"name": "woman", "value": 0.881907045841217, "id": "ai_RQccV41p", "app_id": "main"}, {"name": "two", "value": 0.8541242480278015, "id": "ai_94cQBGlt", "app_id": "main"}, {"name": "wear", "value": 0.8426380157470703, "id": "ai_86sS08Pw", "app_id": "main"}, {"name": "side view", "value": 0.8213586807250977, "id": "ai_XNzGRk0F", "app_id": "main"}, {"name": "dark", "value": 0.774100124835968, "id": "ai_4sJLn6nX", "app_id": "main"}, {"name": "light", "value": 0.7547222971916199, "id": "ai_n9vjC1jB", "app_id": "main"}, {"name": "profile", "value": 0.7413827776908875, "id": "ai_8RFGb5Lw", "app_id": "main"}, {"name": "outdoors", "value": 0.7293674945831299, "id": "ai_Zmhsv0Ch", "app_id": "main"}, {"name": "recreation", "value": 0.7277866005897522, "id": "ai_8Qw6PFLZ", "app_id": "main"}, {"name": "veil", "value": 0.7147266864776611, "id": "ai_L83krFdq", "app_id": "main"}, {"name": "danger", "value": 0.7090088725090027, "id": "ai_6pRrC0WT", "app_id": "main"}, {"name": "offense", "value": 0.6875807046890259, "id": "ai_4dB4Dh6F", "app_id": "main"}, {"name": "indoors", "value": 0.6727075576782227, "id": "ai_Pf2b7clG", "app_id": "main"}, {"name": "festival", "value": 0.6394270658493042, "id": "ai_13NdwKqz", "app_id": "main"}, {"name": "shadow", "value": 0.639357328414917, "id": "ai_27pZT42H", "app_id": "main"}]}, "frame_info": {"time": 31000, "index": 31}}, {"data": {"concepts": [{"name": "people", "value": 0.9946573376655579, "id": "ai_l8TKp2h5", "app_id": "main"}, {"name": "adult", "value": 0.9891029000282288, "id": "ai_VPmHr5bm", "app_id": "main"}, {"name": "man", "value": 0.9572210311889648, "id": "ai_dxSG2s86", "app_id": "main"}, {"name": "portrait", "value": 0.9567321538925171, "id": "ai_TJ9wFfK5", "app_id": "main"}, {"name": "woman", "value": 0.9494471549987793, "id": "ai_RQccV41p", "app_id": "main"}, {"name": "one", "value": 0.9426029920578003, "id": "ai_SVshtN54", "app_id": "main"}, {"name": "nude", "value": 0.9268009662628174, "id": "ai_XdXkh9Vw", "app_id": "main"}, {"name": "mirror", "value": 0.8813271522521973, "id": "ai_D5KjgBR3", "app_id": "main"}, {"name": "side view", "value": 0.8777040243148804, "id": "ai_XNzGRk0F", "app_id": "main"}, {"name": "two", "value": 0.8727242946624756, "id": "ai_94cQBGlt", "app_id": "main"}, {"name": "wear", "value": 0.8426380157470703, "id": "ai_86sS08Pw", "app_id": "main"}, {"name": "profile", "value": 0.837187647819519, "id": "ai_8RFGb5Lw", "app_id": "main"}, {"name": "shirtless", "value": 0.8136011958122253, "id": "ai_Dvvvzjnb", "app_id": "main"}, {"name": "veil", "value": 0.7838930487632751, "id": "ai_L83krFdq", "app_id": "main"}, {"name": "girl", "value": 0.775181770324707, "id": "ai_xQbBc1zb", "app_id": "main"}, {"name": "dark", "value": 0.774100124835968, "id": "ai_4sJLn6nX", "app_id": "main"}, {"name": "fashion", "value": 0.7318723201751709, "id": "ai_dngMN46t", "app_id": "main"}, {"name": "indoors", "value": 0.7143398523330688, "id": "ai_Pf2b7clG", "app_id": "main"}, {"name": "outdoors", "value": 0.6960704326629639, "id": "ai_Zmhsv0Ch", "app_id": "main"}, {"name": "face", "value": 0.6937504410743713, "id": "ai_8jtPl3Xj", "app_id": "main"}]}, "frame_info": {"time": 32000, "index": 32}}, {"data": {"concepts": [{"name": "people", "value": 0.9946573376655579, "id": "ai_l8TKp2h5", "app_id": "main"}, {"name": "adult", "value": 0.9935365915298462, "id": "ai_VPmHr5bm", "app_id": "main"}, {"name": "man", "value": 0.9723907113075256, "id": "ai_dxSG2s86", "app_id": "main"}, {"name": "portrait", "value": 0.9567321538925171, "id": "ai_TJ9wFfK5", "app_id": "main"}, {"name": "woman", "value": 0.9494471549987793, "id": "ai_RQccV41p", "app_id": "main"}, {"name": "one", "value": 0.9426029920578003, "id": "ai_SVshtN54", "app_id": "main"}, {"name": "nude", "value": 0.9268009662628174, "id": "ai_XdXkh9Vw", "app_id": "main"}, {"name": "mirror", "value": 0.8813271522521973, "id": "ai_D5KjgBR3", "app_id": "main"}, {"name": "side view", "value": 0.8777040243148804, "id": "ai_XNzGRk0F", "app_id": "main"}, {"name": "two", "value": 0.8727242946624756, "id": "ai_94cQBGlt", "app_id": "main"}, {"name": "wear", "value": 0.8426380157470703, "id": "ai_86sS08Pw", "app_id": "main"}, {"name": "profile", "value": 0.837187647819519, "id": "ai_8RFGb5Lw", "app_id": "main"}, {"name": "shirtless", "value": 0.8136011958122253, "id": "ai_Dvvvzjnb", "app_id": "main"}, {"name": "veil", "value": 0.7838930487632751, "id": "ai_L83krFdq", "app_id": "main"}, {"name": "dark", "value": 0.7649282217025757, "id": "ai_4sJLn6nX", "app_id": "main"}, {"name": "fashion", "value": 0.7318723201751709, "id": "ai_dngMN46t", "app_id": "main"}, {"name": "indoors", "value": 0.7143398523330688, "id": "ai_Pf2b7clG", "app_id": "main"}, {"name": "outdoors", "value": 0.6960704326629639, "id": "ai_Zmhsv0Ch", "app_id": "main"}, {"name": "offense", "value": 0.6875807046890259, "id": "ai_4dB4Dh6F", "app_id": "main"}, {"name": "looking", "value": 0.6820242404937744, "id": "ai_9fQBzNBM", "app_id": "main"}]}, "frame_info": {"time": 33000, "index": 33}}]